{
  "id": "8de45594-c3e0-4062-aa35-259c74d9849e",
  "prevId": "e8420f2e-bcca-4a4d-8c78-2fa857b8aa04",
  "version": "7",
  "dialect": "postgresql",
  "tables": {
    "public.products": {
      "name": "products",
      "schema": "",
      "columns": {
        "id": {
          "name": "id",
          "type": "serial",
          "primaryKey": true,
          "notNull": true
        },
        "productName": {
          "name": "productName",
          "type": "text",
          "primaryKey": false,
          "notNull": true
        },
        "description": {
          "name": "description",
          "type": "text",
          "primaryKey": false,
          "notNull": false
        },
        "range": {
          "name": "range",
          "type": "text",
          "primaryKey": false,
          "notNull": false
        },
        "index": {
          "name": "index",
          "type": "integer",
          "primaryKey": false,
          "notNull": false
        }
      },
      "indexes": {},
      "foreignKeys": {},
      "compositePrimaryKeys": {},
      "uniqueConstraints": {
        "products_index_unique": {
          "name": "products_index_unique",
          "nullsNotDistinct": false,
          "columns": [
            "index"
          ]
        }
      },
      "policies": {},
      "checkConstraints": {},
      "isRLSEnabled": false
    }
  },
  "enums": {},
  "schemas": {},
  "sequences": {},
  "roles": {},
  "policies": {},
  "views": {},
  "_meta": {
    "columns": {},
    "schemas": {},
    "tables": {}
  }
}